sa818.py
sa818-0.1.9.dist-info/LICENSE
sa818-0.1.9.dist-info/METADATA
sa818-0.1.9.dist-info/WHEEL
sa818-0.1.9.dist-info/entry_points.txt
sa818-0.1.9.dist-info/top_level.txt
sa818-0.1.9.dist-info/RECORD
