Metadata-Version: 2.1
Name: sa818
Version: 0.1.9
Summary: SA818 Programming Software
Home-page: https://github.com/0x9900/SA818/
Author: Fred C. (W6BSD)
Author-email: w6bsd@bsdworld.org
License: BSD
Platform: UNKNOWN
Classifier: Development Status :: 3 - Alpha
Classifier: Intended Audience :: Developers
Classifier: License :: OSI Approved :: BSD License
Classifier: Operating System :: OS Independent
Classifier: Programming Language :: Python
Classifier: Programming Language :: Python :: 3
Classifier: Programming Language :: Python :: 3.5
Classifier: Topic :: Communications :: Ham Radio
Requires-Dist: pyserial
